mlflow_dl/__init__.py
mlflow_dl/__main__.py
mlflow_dl/cli.py
mlflow_dl/logger.py
mlflow_dl/main.py
mlflow_dl/mlflow_helper.py
mlflow_dl-0.2.2.dist-info/METADATA
mlflow_dl-0.2.2.dist-info/WHEEL
mlflow_dl-0.2.2.dist-info/entry_points.txt
mlflow_dl-0.2.2.dist-info/licenses/LICENSE
mlflow_dl-0.2.2.dist-info/RECORD
