Metadata-Version: 2.1
Name: mlflow_dl
Version: 0.2.2
Summary: Package for interaction with MLFlow Registry
Project-URL: Homepage, https://github.com/dem-artem/mlflow_dl
License-Expression: MIT
License-File: LICENSE
Requires-Python: <=3.11,>=3.8
Requires-Dist: boto3
Requires-Dist: click
Requires-Dist: mlflow<1.20.0
Requires-Dist: numpy<=1.20.0
Requires-Dist: protobuf<3.20.0
Requires-Dist: python-dotenv
Requires-Dist: tqdm
Provides-Extra: dev
Requires-Dist: build; extra == 'dev'
Requires-Dist: bumpversion; extra == 'dev'
Requires-Dist: coverage; extra == 'dev'
Requires-Dist: flake8; extra == 'dev'
Requires-Dist: flake8-annotations; extra == 'dev'
Requires-Dist: flake8-unused-arguments; extra == 'dev'
Requires-Dist: twine; extra == 'dev'
